komanawa/gw_age_tools/__init__.py
komanawa/gw_age_tools/exponential_piston_flow.py
komanawa/gw_age_tools/lightweight.py
komanawa/gw_age_tools/source_predictions.py
komanawa/gw_age_tools/version.py
komanawa_gw_age_tools-2.1.2.dist-info/licenses/LICENSE
komanawa_gw_age_tools-2.1.2.dist-info/METADATA
komanawa_gw_age_tools-2.1.2.dist-info/WHEEL
komanawa_gw_age_tools-2.1.2.dist-info/top_level.txt
komanawa_gw_age_tools-2.1.2.dist-info/RECORD
