Metadata-Version: 2.4
Name: komanawa-gw-age-tools
Version: 2.1.2
Summary: A package to manage groundwater age distributions
Author-email: Matt Dumont <Matt@komanawa.com>
License:                    GNU LESSER GENERAL PUBLIC LICENSE
Project-URL: Homepage, https://github.com/Komanawa-Solutions-Ltd/komanawa-gw-age-tools
Project-URL: Issues, https://github.com/Komanawa-Solutions-Ltd/komanawa-gw-age-tools/issues
Project-URL: Documentation, https://komanawa-solutions-ltd.github.io/komanawa-gw-age-tools/
Classifier: Programming Language :: Python :: 3
Classifier: License :: OSI Approved :: GNU Lesser General Public License v3 or later (LGPLv3+)
Classifier: Operating System :: OS Independent
Requires-Python: >=3.11
License-File: LICENSE
Requires-Dist: pandas
Requires-Dist: numpy
Requires-Dist: scipy
Requires-Dist: tables
Dynamic: license-file
